README.rst
setup.py
redcap_cli/__init__.py
redcap_cli/redcap_metadata.py
redcap_cli/redcap_records.py
redcap_cli.egg-info/PKG-INFO
redcap_cli.egg-info/SOURCES.txt
redcap_cli.egg-info/dependency_links.txt
redcap_cli.egg-info/entry_points.txt
redcap_cli.egg-info/requires.txt
redcap_cli.egg-info/top_level.txt