Metadata-Version: 1.0
Name: redcap-cli
Version: 0.1.0
Summary: A suite of command line utilities for REDCap with a focus on API interaction.
Home-page: https://github.com/ctsit/redcap_cli
Author: pbc
Author-email: ctsit@ctsi.ufl.edu
License: Apache 2.0
Platform: UNKNOWN
